mapDisk/__init__.py
mapDisk/mapDisk.py
mapdisk-0.0.1.dist-info/METADATA
mapdisk-0.0.1.dist-info/WHEEL
mapdisk-0.0.1.dist-info/licenses/LICENSE
mapdisk-0.0.1.dist-info/RECORD
