Metadata-Version: 2.1
Name: mapDisk
Version: 0.0.1
Summary: Hashable storage on disk
Project-URL: Homepage, https://github.com/samarthpusalkar/MappingOnDisk
Project-URL: Bug Tracker, https://github.com/samarthpusalkar/MappingOnDisk/issues
Author-email: Samarth Pusalkar <samar29p@gmail.com>
License-File: LICENSE
Classifier: License :: OSI Approved :: MIT License
Classifier: Operating System :: OS Independent
Classifier: Programming Language :: Python :: 3
Requires-Python: >=3.8
